mytoyota/__init__.py
mytoyota/api.py
mytoyota/client.py
mytoyota/const.py
mytoyota/controller.py
mytoyota/exceptions.py
mytoyota/models/dashboard.py
mytoyota/models/electric_status.py
mytoyota/models/endpoints/account.py
mytoyota/models/endpoints/common.py
mytoyota/models/endpoints/electric.py
mytoyota/models/endpoints/location.py
mytoyota/models/endpoints/notifications.py
mytoyota/models/endpoints/service_history.py
mytoyota/models/endpoints/status.py
mytoyota/models/endpoints/telemetry.py
mytoyota/models/endpoints/trips.py
mytoyota/models/endpoints/vehicle_guid.py
mytoyota/models/endpoints/vehicle_health.py
mytoyota/models/location.py
mytoyota/models/lock_status.py
mytoyota/models/nofication.py
mytoyota/models/service_history.py
mytoyota/models/summary.py
mytoyota/models/trips.py
mytoyota/models/vehicle.py
mytoyota/py.typed
mytoyota/utils/__init__.py
mytoyota/utils/conversions.py
mytoyota/utils/formatters.py
mytoyota/utils/helpers.py
mytoyota/utils/locale.py
mytoyota/utils/log_utils.py
mytoyota/utils/models.py
mytoyota-2.2.2.dist-info/LICENSE
mytoyota-2.2.2.dist-info/METADATA
mytoyota-2.2.2.dist-info/WHEEL
mytoyota-2.2.2.dist-info/RECORD
