Metadata-Version: 2.3
Name: mytoyota
Version: 2.2.2
Summary: Python client for Toyota Connected Services.
License: MIT
Keywords: Toyota,Car,MYT
Author: Simon Grud Hansen
Author-email: simongrud@gmail.com
Requires-Python: >=3.9,<4.0
Classifier: Development Status :: 4 - Beta
Classifier: License :: OSI Approved :: MIT License
Classifier: Programming Language :: Python :: 3
Classifier: Programming Language :: Python :: 3.9
Classifier: Programming Language :: Python :: 3.10
Classifier: Programming Language :: Python :: 3.11
Classifier: Programming Language :: Python :: 3.12
Classifier: Programming Language :: Python :: 3.13
Requires-Dist: arrow (>=1.1,<2.0)
Requires-Dist: hishel (>=0.0.19,<0.0.20)
Requires-Dist: httpx (>=0.18.1)
Requires-Dist: importlib-metadata (>=7.0.1,<8.0.0)
Requires-Dist: langcodes (>=3.1,<4.0)
Requires-Dist: pydantic (>=2.10.4,<3.0.0)
Requires-Dist: pyjwt (>=2.8.0,<3.0.0)
Project-URL: Bug Tracker, https://github.com/DurgNomis-drol/mytoyota/issues
Project-URL: Homepage, https://github.com/DurgNomis-drol/mytoyota
Project-URL: Repository, https://github.com/DurgNomis-drol/mytoyota
Project-URL: Release Notes, https://github.com/DurgNomis-drol/mytoyota/releases
